MANIFEST.in
distribute_setup.py
setup.py
oobjlib/__init__.py
oobjlib/common.py
oobjlib/component.py
oobjlib/connection.py
oobjlib/convert.py
oobjlib/exceptions.py
oobjlib/netrpclib.py
oobjlib/release.py
openobject_library.egg-info/PKG-INFO
openobject_library.egg-info/SOURCES.txt
openobject_library.egg-info/dependency_links.txt
openobject_library.egg-info/top_level.txt