Metadata-Version: 1.0
Name: openobject-library
Version: 2.0.2
Summary: Web Services library OpenObject Framework
Home-page: https://launchpad.net/openobject-library
Author: Christophe CHAUVET
Author-email: christophe.chauvet@syleam.fr
License: GPLv3
Platform: UNKNOWN
Classifier: Development Status :: 5 - Production/Stable
Classifier: Environment :: Console
Classifier: License :: OSI Approved :: GNU Affero General Public License v3
Classifier: Operating System :: OS Independent
Classifier: Programming Language :: Python :: 2.4
Classifier: Programming Language :: Python :: 2.5
Classifier: Programming Language :: Python :: 2.6
Classifier: Programming Language :: Python :: 2.7
Classifier: Topic :: Software Development :: Libraries :: Python Modules
